spello/__init__.py
spello/config.py
spello/model.py
spello/settings.py
spello/utils.py
spello/context/__init__.py
spello/context/context.py
spello/phoneme/__init__.py
spello/phoneme/constant.py
spello/phoneme/phoneme.py
spello/symspell/__init__.py
spello/symspell/symspell.py
spello-1.3.0.dist-info/LICENSE
spello-1.3.0.dist-info/METADATA
spello-1.3.0.dist-info/WHEEL
spello-1.3.0.dist-info/top_level.txt
spello-1.3.0.dist-info/RECORD
