Metadata-Version: 2.1
Name: spello
Version: 1.3.0
Summary: Spello: Fast and Smart Spell Correction
Home-page: https://github.com/hellohaptik/spello
Author: Machine Learning Team @ Jio Haptik Technologies Limited
Author-email: machinelearning@haptik.ai
License: UNKNOWN
Keywords: nlp machine learning spell correction
Platform: UNKNOWN
Classifier: Programming Language :: Python :: 3.6
Classifier: License :: OSI Approved :: MIT License
Classifier: Operating System :: OS Independent
Requires-Python: >=3.6
License-File: LICENSE
Requires-Dist: nltk (<4,>=3.4.5)
